Control_Unit.v
module Control_Unit(j , halt , lw , sw , alu , addi , beq, instruction);
    output j, halt, lw, sw, alu, addi, beq;
    input [5:0] instruction;

    reg j;
    reg halt;
    reg lw;
    reg sw;
    reg alu;
    reg addi;
    reg beq;

    initial begin
        j <= 0;
        halt <= 0;
        lw <= 0;
        sw <= 0;
        alu <= 0;
        addi <= 0;
        beq <= 0;
    end

    always @(*) begin
        j <= instruction == 2;
        halt <= instruction == 63;
        lw <= instruction == 35;
        sw <= instruction == 43;
        alu <= instruction == 0;
        addi <= instruction == 8;
        beq <= instruction == 4;
    end
endmodule

// Módulo de testeo, envía la señal de reloj al flip-flop
module tester(j , halt , lw , sw , alu , addi , beq, instruction, clk);
    input j, halt, lw, sw, alu, addi, beq;
    output [5:0] instruction;
    output clk;

    reg [5:0] instruction;
    reg clk;

	// Correr el test sólo una vez
	initial
	begin
		// Inicializar el reloj
		clk = 0;
		// Volcar los resultados de la simulación en el archivo Memoria_datos.vcd
		$dumpfile("Control_Unit_Out.vcd");
		$dumpvars;
		// Generar las señales de entrada j y k
		instruction = 6'b000000;
        #1 instruction = 6'b000010;
		#1 instruction = 6'b000100;
        #1 instruction = 6'b001000; 
        #1 instruction = 6'b100011;
        #1 instruction = 6'b101011;
        #1 instruction = 6'b111111;
        #1 instruction = 6'b000000;
		#1 $finish;
	end

	// Generar la señal de reloj periódica
	always
	begin
		#1 clk=!clk;
	end
endmodule

// El banco de pruebas conecta el tester 
module testbench;
	wire clk, j, halt, lw, sw, alu, addi, beq;
    wire [5:0] instruction;
	Control_Unit flipflop1(j , halt , lw , sw , alu , addi , beq, instruction);
	tester test1(j , halt , lw , sw , alu , addi , beq, instruction, clk);
endmodule

Control_Unit_Out.vcd
$date
	Tue Dec 14 17:05:41 2021
$end
$version
	Icarus Verilog
$end
$timescale
	1s
$end
$scope module testbench $end
$var wire 1 ! sw $end
$var wire 1 " lw $end
$var wire 1 # j $end
$var wire 6 $ instruction [5:0] $end
$var wire 1 % halt $end
$var wire 1 & clk $end
$var wire 1 ' beq $end
$var wire 1 ( alu $end
$var wire 1 ) addi $end
$scope module flipflop1 $end
$var wire 6 * instruction [5:0] $end
$var reg 1 ) addi $end
$var reg 1 ( alu $end
$var reg 1 ' beq $end
$var reg 1 % halt $end
$var reg 1 # j $end
$var reg 1 " lw $end
$var reg 1 ! sw $end
$upscope $end
$scope module test1 $end
$var wire 1 ) addi $end
$var wire 1 ( alu $end
$var wire 1 ' beq $end
$var wire 1 % halt $end
$var wire 1 # j $end
$var wire 1 " lw $end
$var wire 1 ! sw $end
$var reg 1 & clk $end
$var reg 6 + instruction [5:0] $end
$upscope $end
$upscope $end
$enddefinitions $end
#0
$dumpvars
b0 +
b0 *
0)
1(
0'
0&
0%
b0 $
0#
0"
0!
$end
#1
0(
1#
1&
b10 $
b10 *
b10 +
#2
1'
0#
0&
b100 $
b100 *
b100 +
#3
0'
1#
1&
b10 $
b10 *
b10 +
#4
1(
0#
0&
b0 $
b0 *
b0 +
#5
1)
0(
1&
b1000 $
b1000 *
b1000 +
#6
0)
1"
0&
b100011 $
b100011 *
b100011 +
#7
1!
0"
1&
b101011 $
b101011 *
b101011 +
#8
0!
1%
0&
b111111 $
b111111 *
b111111 +
